cppython_meson/__init__.py
cppython_meson/plugin.py
cppython_meson/py.typed
cppython_meson/resolution.py
cppython_meson/schema.py
cppython_meson-0.1.0.dev2.dist-info/entry_points.txt
cppython_meson-0.1.0.dev2.dist-info/WHEEL
cppython_meson-0.1.0.dev2.dist-info/METADATA
cppython_meson-0.1.0.dev2.dist-info/licenses/LICENSE.md
cppython_meson-0.1.0.dev2.dist-info/RECORD
